Popdata/Analyze.py
Popdata/Evaluator.py
Popdata/Generator.py
Popdata/__init__.py
Popdata/main.py
PopulateData-1.0.0.dist-info/DESCRIPTION.rst
PopulateData-1.0.0.dist-info/METADATA
PopulateData-1.0.0.dist-info/RECORD
PopulateData-1.0.0.dist-info/WHEEL
PopulateData-1.0.0.dist-info/metadata.json
PopulateData-1.0.0.dist-info/top_level.txt
