Metadata-Version: 2.0
Name: PopulateData
Version: 1.0.0
Summary: Populate / generate data based on certain conditions
Home-page: https://github.com/JuneSunshine/Magic_Square
Author: JuneSunshine
Author-email: ljygeek@gmail.com
License: MIT Licence
Keywords: populatedata python3 package
Platform: all
